bloqade/geometry/__init__.py
bloqade/geometry/prelude.py
bloqade/geometry/dialects/__init__.py
bloqade/geometry/dialects/filled/__init__.py
bloqade/geometry/dialects/filled/_dialect.py
bloqade/geometry/dialects/filled/_interface.py
bloqade/geometry/dialects/filled/concrete.py
bloqade/geometry/dialects/filled/stmts.py
bloqade/geometry/dialects/filled/types.py
bloqade/geometry/dialects/grid/__init__.py
bloqade/geometry/dialects/grid/_dialect.py
bloqade/geometry/dialects/grid/_interface.py
bloqade/geometry/dialects/grid/_typeinfer.py
bloqade/geometry/dialects/grid/concrete.py
bloqade/geometry/dialects/grid/stmts.py
bloqade/geometry/dialects/grid/types.py
bloqade/geometry/rewrite/__init__.py
bloqade/geometry/rewrite/desugar.py
bloqade_geometry-0.5.1.dist-info/METADATA
bloqade_geometry-0.5.1.dist-info/WHEEL
bloqade_geometry-0.5.1.dist-info/licenses/LICENSE
bloqade_geometry-0.5.1.dist-info/RECORD
