Metadata-Version: 2.4
Name: bloqade-geometry
Version: 0.5.1
Summary: Components for defining and manipulating geometric objects in Bloqade for neutral atom quantum computing.
Author-email: Phillip Weinberg <pweinberg@quera.com>
License-File: LICENSE
Requires-Python: >=3.10
Requires-Dist: kirin-toolchain~=0.22.0
